pnpl/__init__.py
pnpl/datasets/__init__.py
pnpl/datasets/constants.py
pnpl/datasets/grouped_dataset.py
pnpl/datasets/noise_dataset.py
pnpl/datasets/preload_dataset.py
pnpl/datasets/utils.py
pnpl/datasets/hdf5/__init__.py
pnpl/datasets/hdf5/dataset.py
pnpl/datasets/hdf5/preprocess.py
pnpl/datasets/libribrain2025/__init__.py
pnpl/datasets/libribrain2025/base.py
pnpl/datasets/libribrain2025/calculate_means_and_stds.py
pnpl/datasets/libribrain2025/competition_holdout_dataset.py
pnpl/datasets/libribrain2025/constants.py
pnpl/datasets/libribrain2025/constants_utils.py
pnpl/datasets/libribrain2025/phoneme_dataset.py
pnpl/datasets/libribrain2025/preprocess.py
pnpl/datasets/libribrain2025/remote_constants.py
pnpl/datasets/libribrain2025/speech_dataset.py
pnpl/datasets/libribrain2025/speech_dataset_holdout.py
pnpl-0.0.7.dist-info/licenses/LICENSE
pnpl-0.0.7.dist-info/METADATA
pnpl-0.0.7.dist-info/WHEEL
pnpl-0.0.7.dist-info/top_level.txt
pnpl-0.0.7.dist-info/RECORD
