Metadata-Version: 2.4
Name: pnpl
Version: 0.0.7
Summary: Load and process brain datasets for deep learning
Home-page: https://github.com/neural-processing-lab/pnpl
Author: Dulhan Jayalath
Author-email: dulhan@robots.ox.ac.uk
Classifier: Programming Language :: Python :: 3
Classifier: Programming Language :: Python :: 3.10
License-File: LICENSE
Requires-Dist: mne
Requires-Dist: mne_bids
Requires-Dist: numpy
Requires-Dist: pandas
Requires-Dist: torch
Requires-Dist: h5py
Requires-Dist: huggingface_hub
Dynamic: author
Dynamic: author-email
Dynamic: classifier
Dynamic: description
Dynamic: description-content-type
Dynamic: home-page
Dynamic: license-file
Dynamic: requires-dist
Dynamic: summary
